spi_master.sv
// Code your design here
module spi_master(clk, mosi, miso, sck, nss, buffer,bufferReg, flag); //DUT code start
  input  miso;
  input  clk;
  output reg  mosi;
  output sck;
  output  nss;
  input reg [15:0] buffer;
  
  reg clear = 0;
  output wire [15:0] bufferReg;
  reg [15:0] shiftReg = 16'b10;
  input reg [7:0 ]flag; 	
always @(posedge clk )
  begin
    if(flag == 8'b0)begin
    shiftReg = buffer;
    end
    if (clear)
    shiftReg <= 16'b0;
    else
    shiftReg <= shiftReg >> 1;
    shiftReg[15] <= miso;
    mosi = shiftReg[0];
    end
assign bufferReg = shiftReg;
  
endmodule //DUT code end

spi_master_tb.sv
// Code your testbench here
// or browse Examples
module spi_master_tb(); //TestBench code start
  reg miso;
  reg clk;
  wire  mosi;
  wire sck;
  wire nss;
  wire [15:0] bufferReg ;
  reg [15:0] buffer;
  reg [7:0] flag;
  
  integer count;
  spi_master UUT(.miso(miso), .mosi(mosi), .sck(sck), .nss(nss), .clk(clk), .buffer(buffer), .bufferReg(bufferReg) , .flag(flag));

initial
 begin
 
   $monitor(" ",miso," ",mosi," ",clk," ",buffer, " ", bufferReg, " ", flag);


   $dumpfile("dump.vcd");
   $dumpvars;
   $dumpvars(8,miso,mosi,sck,nss,clk, buffer,bufferReg,flag);
 
  miso = 1'b0;
  clk = 1'b0;
   buffer = 16'd10;
   flag = 8'b0;
  for (count = 0; count < 16; count = count + 1'b1) 
  
   begin
     #100
   miso = ~miso;
     
   clk = ~clk;
  
     if(count == 2)begin
       flag = 8'b1;
     end
   
   end
   


end
endmodule //TestBench code end

dump.vcd
$date
Thu Feb 10 11:43:52 2022
$end
$version
Riviera-PRO Version 2020.04.130.7729
$end
$timescale
1 ns
$end

$scope module spi_master_tb $end
$var wire 1 ! mosi $end
$var wire 1 " sck $end
$var wire 1 " nss $end
$var wire 16 # bufferReg [15:0] $end
$var reg 1 $ miso $end
$var reg 1 % clk $end
$var reg 16 & buffer [15:0] $end
$var reg 8 ' flag [7:0] $end
$var integer 32 ( count $end

$scope module UUT $end
$var wire 1 ) clk $end
$var wire 1 * miso $end
$var wire 1 " sck $end
$var wire 1 " nss $end
$var wire 16 # bufferReg [15:0] $end
$var reg 1 + mosi $end
$var reg 16 , buffer [15:0] $end
$var reg 8 - flag [7:0] $end
$var reg 1 . clear $end
$var reg 16 / shiftReg [15:0] $end
$upscope $end

$upscope $end

$enddefinitions $end
$dumpvars
x!
z"
b10 #
0$
0%
b1010 &
b0 '
b0 (
0)
0*
x+
b1010 ,
b0 -
0.
b10 /
$end
#100
1$
1%
b1 (
1)
1*
b1010 /
0+
b1010 #
0!
b1000000000000101 /
b1000000000000101 #
#200
0$
0%
b10 (
0)
0*
#300
1$
1%
b1 '
b11 (
b1 -
1)
1*
1+
1!
b1100000000000010 /
b1100000000000010 #
#400
0$
0%
b100 (
0)
0*
#500
1$
1%
b101 (
1)
1*
0+
0!
b1110000000000001 /
b1110000000000001 #
#600
0$
0%
b110 (
0)
0*
#700
1$
1%
b111 (
1)
1*
1+
1!
b1111000000000000 /
b1111000000000000 #
#800
0$
0%
b1000 (
0)
0*
#900
1$
1%
b1001 (
1)
1*
0+
0!
b1111100000000000 /
b1111100000000000 #
#1000
0$
0%
b1010 (
0)
0*
